random_forest_model/VERSION
random_forest_model/__init__.py
random_forest_model/pipeline.py
random_forest_model/predict.py
random_forest_model/train_model.py
random_forest_model/train_pipeline.py
random_forest_model/config/__init__.py
random_forest_model/config/core.py
random_forest_model/processing/__init__.py
random_forest_model/processing/data_management.py
random_forest_model/processing/errors.py
random_forest_model/processing/preprocessors.py
random_forest_model/processing/validation.py
TRIQ_Model-0.1.dist-info/METADATA
TRIQ_Model-0.1.dist-info/WHEEL
TRIQ_Model-0.1.dist-info/top_level.txt
TRIQ_Model-0.1.dist-info/RECORD
